LEGAL.txt
kairos_ark-0.1.8.dist-info/METADATA
kairos_ark-0.1.8.dist-info/WHEEL
kairos_ark/__init__.py
kairos_ark/_core.pypy311-pp73-x86_64-linux-gnu.so
kairos_ark/agent.py
kairos_ark/connectors/__init__.py
kairos_ark/connectors/anthropic.py
kairos_ark/connectors/base.py
kairos_ark/connectors/cohere.py
kairos_ark/connectors/gemini.py
kairos_ark/connectors/mistral.py
kairos_ark/connectors/ollama.py
kairos_ark/connectors/openai.py
kairos_ark/integrations/__init__.py
kairos_ark/integrations/crewai.py
kairos_ark/integrations/langgraph.py
kairos_ark/tools.py
kairos_ark-0.1.8.dist-info/RECORD
