Metadata-Version: 2.4
Name: kairos_ark
Version: 0.1.8
Classifier: Programming Language :: Rust
Classifier: Programming Language :: Python :: Implementation :: CPython
Classifier: Programming Language :: Python :: 3
Classifier: Programming Language :: Python :: 3.8
Classifier: Programming Language :: Python :: 3.9
Classifier: Programming Language :: Python :: 3.10
Classifier: Programming Language :: Python :: 3.11
Classifier: Programming Language :: Python :: 3.12
Classifier: License :: OSI Approved :: MIT License
Summary: KAIROS-ARK: A deterministic multi-threaded scheduler for agentic AI workflows
Author: YASSERRMD
License: MIT
Requires-Python: >=3.8, <3.14
